bcra/__init__.py
bcra/base.py
bcra/client.py
bcra/config.py
bcra/exceptions.py
bcra/currency/__init__.py
bcra/currency/dollar.py
bcra/statistics/__init__.py
bcra/statistics/variables.py
bcra_api_client-1.2.0.dist-info/LICENSE
bcra_api_client-1.2.0.dist-info/METADATA
bcra_api_client-1.2.0.dist-info/WHEEL
bcra_api_client-1.2.0.dist-info/top_level.txt
bcra_api_client-1.2.0.dist-info/RECORD
